{
  "project_info": {
    "project_number": "445891553108",
    "project_id": "ecommerce-86981",
    "storage_bucket": "ecommerce-86981.appspot.com"
  },
  "client": [
    {
      "client_info": {
        "mobilesdk_app_id": "1:445891553108:android:2d37b68edc21762d164ac1",
        "android_client_info": {
          "package_name": "com.example.e_comm"
        }
      },
      "oauth_client": [],
      "api_key": [
        {
          "current_key": "AIzaSyAUeTbi7XEYD_BsW8LPS5ozD9ykk4FX_m4"
        }
      ],
      "services": {
        "appinvite_service": {
          "other_platform_oauth_client": []
        }
      }
    }
  ],
  "configuration_version": "1"
}